{
  "generated_at": "2026-06-19T06:20:17.608902+00:00",
  "note": "YouTube project relevance summary; TikTok guideline v1 adapter.",
  "rows": [
    {
      "project_id": 14,
      "project_name": "京剧",
      "list_type": "RL",
      "category": "表演艺术(戏曲)",
      "unique_videos": 417,
      "likely_relevant": 397,
      "needs_review": 13,
      "low_relevance": 7,
      "likely_ratio": 0.952,
      "needs_review_ratio": 0.0312,
      "low_relevance_ratio": 0.0168,
      "avg_quality_score": 5.935,
      "negative_hit_videos": 0,
      "negative_hit_ratio": 0.0,
      "weak_generic_source_videos": 0,
      "weak_generic_source_ratio": 0.0,
      "three_page_lower_bound_videos": 0,
      "three_page_lower_bound_ratio": 0.0,
      "collection_state_counts": {
        "ceiling_capped_500": 417
      },
      "total_play_likely": 14147314,
      "total_play_needs_review": 1321342,
      "total_play_low_relevance": 4528643,
      "max_play_likely": 2952390,
      "max_play_needs_review": 1046198,
      "max_play_low_relevance": 4508294,
      "top_quality_reasons": {
        "source_hit": 390,
        "china_context": 319,
        "project_term_hits:1": 244,
        "core_term_hits:1": 244,
        "cjk_text": 165,
        "project_term_hits:2": 101,
        "core_term_hits:2": 101,
        "project_term_hits:3": 37
      },
      "top_negative_terms": {}
    },
    {
      "project_id": 15,
      "project_name": "中医针灸",
      "list_type": "RL",
      "category": "传统医药",
      "unique_videos": 398,
      "likely_relevant": 243,
      "needs_review": 141,
      "low_relevance": 14,
      "likely_ratio": 0.6106,
      "needs_review_ratio": 0.3543,
      "low_relevance_ratio": 0.0352,
      "avg_quality_score": 4.804,
      "negative_hit_videos": 0,
      "negative_hit_ratio": 0.0,
      "weak_generic_source_videos": 0,
      "weak_generic_source_ratio": 0.0,
      "three_page_lower_bound_videos": 0,
      "three_page_lower_bound_ratio": 0.0,
      "collection_state_counts": {
        "exhausted": 398
      },
      "total_play_likely": 5917045,
      "total_play_needs_review": 980537,
      "total_play_low_relevance": 40703,
      "max_play_likely": 1464268,
      "max_play_needs_review": 306579,
      "max_play_low_relevance": 17443,
      "top_quality_reasons": {
        "china_context": 309,
        "project_term_hits:2": 161,
        "core_term_hits:2": 161,
        "project_term_hits:1": 143,
        "core_term_hits:1": 143,
        "source_hit": 120,
        "project_term_hits:3": 56,
        "core_term_hits:3": 56
      },
      "top_negative_terms": {}
    },
    {
      "project_id": 24,
      "project_name": "宣纸传统制作技艺",
      "list_type": "RL",
      "category": "传统手工艺",
      "unique_videos": 420,
      "likely_relevant": 179,
      "needs_review": 212,
      "low_relevance": 29,
      "likely_ratio": 0.4262,
      "needs_review_ratio": 0.5048,
      "low_relevance_ratio": 0.069,
      "avg_quality_score": 3.79,
      "negative_hit_videos": 0,
      "negative_hit_ratio": 0.0,
      "weak_generic_source_videos": 0,
      "weak_generic_source_ratio": 0.0,
      "three_page_lower_bound_videos": 0,
      "three_page_lower_bound_ratio": 0.0,
      "collection_state_counts": {
        "ceiling_capped_500": 420
      },
      "total_play_likely": 26093428,
      "total_play_needs_review": 15058229,
      "total_play_low_relevance": 10307333,
      "max_play_likely": 10852273,
      "max_play_needs_review": 9249788,
      "max_play_low_relevance": 8575619,
      "top_quality_reasons": {
        "china_context": 349,
        "project_term_hits:1": 203,
        "core_term_hits:1": 203,
        "project_term_hits:2": 115,
        "core_term_hits:2": 115,
        "cjk_text": 81,
        "project_term_hits:3": 41,
        "core_term_hits:3": 41
      },
      "top_negative_terms": {}
    },
    {
      "project_id": 31,
      "project_name": "蒙古族呼麦",
      "list_type": "RL",
      "category": "表演艺术(音乐)",
      "unique_videos": 718,
      "likely_relevant": 354,
      "needs_review": 115,
      "low_relevance": 249,
      "likely_ratio": 0.493,
      "needs_review_ratio": 0.1602,
      "low_relevance_ratio": 0.3468,
      "avg_quality_score": 3.153,
      "negative_hit_videos": 455,
      "negative_hit_ratio": 0.6337,
      "weak_generic_source_videos": 0,
      "weak_generic_source_ratio": 0.0,
      "three_page_lower_bound_videos": 0,
      "three_page_lower_bound_ratio": 0.0,
      "collection_state_counts": {
        "ceiling_capped_500": 409,
        "exhausted": 309
      },
      "total_play_likely": 66374156,
      "total_play_needs_review": 69476721,
      "total_play_low_relevance": 296156183,
      "max_play_likely": 39450861,
      "max_play_needs_review": 38681680,
      "max_play_low_relevance": 124078553,
      "top_quality_reasons": {
        "china_context": 496,
        "source_hit": 368,
        "core_term_hits:1": 347,
        "negative_term_hits:1": 296,
        "project_term_hits:2": 242,
        "project_term_hits:3": 132,
        "cjk_text": 132,
        "core_term_hits:2": 104
      },
      "top_negative_terms": {
        "mongolia": 358,
        "tuva": 172,
        "tuvan": 136,
        "huunhuurtu": 30,
        "alash": 11,
        "mongoliansinger": 5,
        "ulaanbaatar": 4
      }
    },
    {
      "project_id": 38,
      "project_name": "端午节",
      "list_type": "RL",
      "category": "节庆民俗",
      "unique_videos": 835,
      "likely_relevant": 787,
      "needs_review": 31,
      "low_relevance": 17,
      "likely_ratio": 0.9425,
      "needs_review_ratio": 0.0371,
      "low_relevance_ratio": 0.0204,
      "avg_quality_score": 7.103,
      "negative_hit_videos": 0,
      "negative_hit_ratio": 0.0,
      "weak_generic_source_videos": 0,
      "weak_generic_source_ratio": 0.0,
      "three_page_lower_bound_videos": 0,
      "three_page_lower_bound_ratio": 0.0,
      "collection_state_counts": {
        "ceiling_capped_500": 835
      },
      "total_play_likely": 80969598,
      "total_play_needs_review": 3231747,
      "total_play_low_relevance": 486597,
      "max_play_likely": 21383816,
      "max_play_needs_review": 902623,
      "max_play_low_relevance": 424961,
      "top_quality_reasons": {
        "source_hit": 772,
        "china_context": 660,
        "project_term_hits:2": 293,
        "core_term_hits:2": 293,
        "cjk_text": 244,
        "project_term_hits:3": 215,
        "core_term_hits:3": 215,
        "project_term_hits:1": 155
      },
      "top_negative_terms": {}
    }
  ]
}